galaxy_bundle/__init__.py
galaxy_bundle/__main__.py
galaxy_bundle/cli.py
galaxy_bundle/info.py
galaxy_bundle/py.typed
galaxy_bundle/versions.py
galaxy_bundle-0.2.1.dist-info/METADATA
galaxy_bundle-0.2.1.dist-info/WHEEL
galaxy_bundle-0.2.1.dist-info/entry_points.txt
galaxy_bundle-0.2.1.dist-info/licenses/LICENSE
galaxy_bundle-0.2.1.dist-info/RECORD
