Metadata-Version: 2.4
Name: galaxy-bundle
Version: 0.2.1
Summary: A BOM-style dependency management package for Python, similar to Spring Boot Parent
Project-URL: Homepage, https://github.com/phodal/galaxy-bundle
Project-URL: Documentation, https://github.com/phodal/galaxy-bundle#readme
Project-URL: Repository, https://github.com/phodal/galaxy-bundle
Project-URL: Issues, https://github.com/phodal/galaxy-bundle/issues
Author-email: Galaxy Team <galaxy@example.com>
License-Expression: MIT
License-File: LICENSE
Keywords: bom,bundle,dependency-management,starter
Classifier: Development Status :: 4 - Beta
Classifier: Intended Audience :: Developers
Classifier: License :: OSI Approved :: MIT License
Classifier: Programming Language :: Python :: 3
Classifier: Programming Language :: Python :: 3.9
Classifier: Programming Language :: Python :: 3.10
Classifier: Programming Language :: Python :: 3.11
Classifier: Programming Language :: Python :: 3.12
Classifier: Topic :: Software Development :: Libraries :: Python Modules
Requires-Python: >=3.9
Provides-Extra: all
Requires-Dist: aiohttp==3.9.0; extra == 'all'
Requires-Dist: aiomysql==0.2.0; extra == 'all'
Requires-Dist: alembic==1.13.0; extra == 'all'
Requires-Dist: asyncpg==0.29.0; extra == 'all'
Requires-Dist: confluent-kafka==2.3.0; extra == 'all'
Requires-Dist: factory-boy==3.3.0; extra == 'all'
Requires-Dist: faker==22.0.0; extra == 'all'
Requires-Dist: fastapi==0.109.0; extra == 'all'
Requires-Dist: hiredis==2.3.2; extra == 'all'
Requires-Dist: httpx==0.26.0; extra == 'all'
Requires-Dist: ipython==8.20.0; extra == 'all'
Requires-Dist: motor==3.3.0; extra == 'all'
Requires-Dist: mypy==1.8.0; extra == 'all'
Requires-Dist: numpy==1.26.0; extra == 'all'
Requires-Dist: openai==1.10.0; extra == 'all'
Requires-Dist: opentelemetry-api==1.22.0; extra == 'all'
Requires-Dist: opentelemetry-instrumentation==0.43b0; extra == 'all'
Requires-Dist: opentelemetry-sdk==1.22.0; extra == 'all'
Requires-Dist: pandas==2.1.0; extra == 'all'
Requires-Dist: pre-commit==3.6.0; extra == 'all'
Requires-Dist: prometheus-client==0.19.0; extra == 'all'
Requires-Dist: psycopg2-binary==2.9.9; extra == 'all'
Requires-Dist: pydantic-settings==2.1.0; extra == 'all'
Requires-Dist: pydantic==2.5.0; extra == 'all'
Requires-Dist: pymongo==4.6.0; extra == 'all'
Requires-Dist: pymysql==1.1.0; extra == 'all'
Requires-Dist: pytest-asyncio==0.23.0; extra == 'all'
Requires-Dist: pytest-cov==4.1.0; extra == 'all'
Requires-Dist: pytest-mock==3.12.0; extra == 'all'
Requires-Dist: pytest==8.0.0; extra == 'all'
Requires-Dist: python-json-logger==2.0.0; extra == 'all'
Requires-Dist: redis==5.0.0; extra == 'all'
Requires-Dist: ruff==0.1.0; extra == 'all'
Requires-Dist: sqlalchemy==2.0.0; extra == 'all'
Requires-Dist: structlog==24.1.0; extra == 'all'
Requires-Dist: tiktoken==0.5.0; extra == 'all'
Requires-Dist: uvicorn[standard]==0.27.0; extra == 'all'
Provides-Extra: api
Requires-Dist: alembic==1.13.0; extra == 'api'
Requires-Dist: asyncpg==0.29.0; extra == 'api'
Requires-Dist: fastapi==0.109.0; extra == 'api'
Requires-Dist: hiredis==2.3.2; extra == 'api'
Requires-Dist: opentelemetry-api==1.22.0; extra == 'api'
Requires-Dist: opentelemetry-instrumentation==0.43b0; extra == 'api'
Requires-Dist: opentelemetry-sdk==1.22.0; extra == 'api'
Requires-Dist: prometheus-client==0.19.0; extra == 'api'
Requires-Dist: psycopg2-binary==2.9.9; extra == 'api'
Requires-Dist: pydantic-settings==2.1.0; extra == 'api'
Requires-Dist: pydantic==2.5.0; extra == 'api'
Requires-Dist: redis==5.0.0; extra == 'api'
Requires-Dist: sqlalchemy==2.0.0; extra == 'api'
Requires-Dist: uvicorn[standard]==0.27.0; extra == 'api'
Provides-Extra: celery
Requires-Dist: celery==5.3.0; extra == 'celery'
Requires-Dist: redis==5.0.0; extra == 'celery'
Provides-Extra: data
Requires-Dist: numpy==1.26.0; extra == 'data'
Requires-Dist: pandas==2.1.0; extra == 'data'
Provides-Extra: dev
Requires-Dist: ipython==8.20.0; extra == 'dev'
Requires-Dist: mypy==1.8.0; extra == 'dev'
Requires-Dist: pre-commit==3.6.0; extra == 'dev'
Requires-Dist: ruff==0.1.0; extra == 'dev'
Provides-Extra: django
Requires-Dist: django==5.0; extra == 'django'
Requires-Dist: djangorestframework==3.14.0; extra == 'django'
Provides-Extra: fastapi
Requires-Dist: fastapi==0.109.0; extra == 'fastapi'
Requires-Dist: pydantic-settings==2.1.0; extra == 'fastapi'
Requires-Dist: pydantic==2.5.0; extra == 'fastapi'
Requires-Dist: uvicorn[standard]==0.27.0; extra == 'fastapi'
Provides-Extra: flask
Requires-Dist: flask-cors==4.0.0; extra == 'flask'
Requires-Dist: flask==3.0.0; extra == 'flask'
Requires-Dist: gunicorn==21.0.0; extra == 'flask'
Provides-Extra: http
Requires-Dist: aiohttp==3.9.0; extra == 'http'
Requires-Dist: httpx==0.26.0; extra == 'http'
Provides-Extra: kafka
Requires-Dist: confluent-kafka==2.3.0; extra == 'kafka'
Provides-Extra: kafka-python
Requires-Dist: kafka-python==2.0.2; extra == 'kafka-python'
Provides-Extra: langchain
Requires-Dist: langchain-community==0.0.10; extra == 'langchain'
Requires-Dist: langchain-core==0.1.0; extra == 'langchain'
Requires-Dist: langchain==0.1.0; extra == 'langchain'
Provides-Extra: logging
Requires-Dist: python-json-logger==2.0.0; extra == 'logging'
Requires-Dist: structlog==24.1.0; extra == 'logging'
Provides-Extra: microservice
Requires-Dist: aiohttp==3.9.0; extra == 'microservice'
Requires-Dist: alembic==1.13.0; extra == 'microservice'
Requires-Dist: asyncpg==0.29.0; extra == 'microservice'
Requires-Dist: confluent-kafka==2.3.0; extra == 'microservice'
Requires-Dist: fastapi==0.109.0; extra == 'microservice'
Requires-Dist: hiredis==2.3.2; extra == 'microservice'
Requires-Dist: httpx==0.26.0; extra == 'microservice'
Requires-Dist: opentelemetry-api==1.22.0; extra == 'microservice'
Requires-Dist: opentelemetry-instrumentation==0.43b0; extra == 'microservice'
Requires-Dist: opentelemetry-sdk==1.22.0; extra == 'microservice'
Requires-Dist: prometheus-client==0.19.0; extra == 'microservice'
Requires-Dist: psycopg2-binary==2.9.9; extra == 'microservice'
Requires-Dist: pydantic-settings==2.1.0; extra == 'microservice'
Requires-Dist: pydantic==2.5.0; extra == 'microservice'
Requires-Dist: python-json-logger==2.0.0; extra == 'microservice'
Requires-Dist: redis==5.0.0; extra == 'microservice'
Requires-Dist: sqlalchemy==2.0.0; extra == 'microservice'
Requires-Dist: structlog==24.1.0; extra == 'microservice'
Requires-Dist: uvicorn[standard]==0.27.0; extra == 'microservice'
Provides-Extra: mongodb
Requires-Dist: motor==3.3.0; extra == 'mongodb'
Requires-Dist: pymongo==4.6.0; extra == 'mongodb'
Provides-Extra: mysql
Requires-Dist: aiomysql==0.2.0; extra == 'mysql'
Requires-Dist: pymysql==1.1.0; extra == 'mysql'
Provides-Extra: observability
Requires-Dist: opentelemetry-api==1.22.0; extra == 'observability'
Requires-Dist: opentelemetry-instrumentation==0.43b0; extra == 'observability'
Requires-Dist: opentelemetry-sdk==1.22.0; extra == 'observability'
Requires-Dist: prometheus-client==0.19.0; extra == 'observability'
Provides-Extra: openai
Requires-Dist: openai==1.10.0; extra == 'openai'
Requires-Dist: tiktoken==0.5.0; extra == 'openai'
Provides-Extra: postgres
Requires-Dist: asyncpg==0.29.0; extra == 'postgres'
Requires-Dist: psycopg2-binary==2.9.9; extra == 'postgres'
Provides-Extra: rabbitmq
Requires-Dist: pika==1.3.0; extra == 'rabbitmq'
Provides-Extra: redis
Requires-Dist: hiredis==2.3.2; extra == 'redis'
Requires-Dist: redis==5.0.0; extra == 'redis'
Provides-Extra: requests
Requires-Dist: requests==2.31.0; extra == 'requests'
Requires-Dist: urllib3==2.1.0; extra == 'requests'
Provides-Extra: sqlalchemy
Requires-Dist: alembic==1.13.0; extra == 'sqlalchemy'
Requires-Dist: sqlalchemy==2.0.0; extra == 'sqlalchemy'
Provides-Extra: testing
Requires-Dist: factory-boy==3.3.0; extra == 'testing'
Requires-Dist: faker==22.0.0; extra == 'testing'
Requires-Dist: httpx==0.26.0; extra == 'testing'
Requires-Dist: pytest-asyncio==0.23.0; extra == 'testing'
Requires-Dist: pytest-cov==4.1.0; extra == 'testing'
Requires-Dist: pytest-mock==3.12.0; extra == 'testing'
Requires-Dist: pytest==8.0.0; extra == 'testing'
Provides-Extra: web
Requires-Dist: aiohttp==3.9.0; extra == 'web'
Requires-Dist: fastapi==0.109.0; extra == 'web'
Requires-Dist: hiredis==2.3.2; extra == 'web'
Requires-Dist: httpx==0.26.0; extra == 'web'
Requires-Dist: pydantic-settings==2.1.0; extra == 'web'
Requires-Dist: pydantic==2.5.0; extra == 'web'
Requires-Dist: redis==5.0.0; extra == 'web'
Requires-Dist: uvicorn[standard]==0.27.0; extra == 'web'
Provides-Extra: worker
Requires-Dist: alembic==1.13.0; extra == 'worker'
Requires-Dist: asyncpg==0.29.0; extra == 'worker'
Requires-Dist: celery==5.3.0; extra == 'worker'
Requires-Dist: hiredis==2.3.2; extra == 'worker'
Requires-Dist: opentelemetry-api==1.22.0; extra == 'worker'
Requires-Dist: opentelemetry-instrumentation==0.43b0; extra == 'worker'
Requires-Dist: opentelemetry-sdk==1.22.0; extra == 'worker'
Requires-Dist: prometheus-client==0.19.0; extra == 'worker'
Requires-Dist: psycopg2-binary==2.9.9; extra == 'worker'
Requires-Dist: redis==5.0.0; extra == 'worker'
Requires-Dist: sqlalchemy==2.0.0; extra == 'worker'
